numkl
tests
