Metadata-Version: 1.1
Name: numkl
Version: 0.0.4
Summary: A thin cython/python wrapper on some routines from Intel MKL
Home-page: https://github.com/refraction-ray/numkl
Author: refraction-ray
Author-email: refraction-ray@protonmail.com
License: UNKNOWN
Platform: UNKNOWN
Classifier: Programming Language :: Python :: 3
Classifier: License :: OSI Approved :: MIT License
